carbus_async/__init__.py
carbus_async/can_router.py
carbus_async/device.py
carbus_async/exceptions.py
carbus_async/messages.py
carbus_async/periodic.py
carbus_async/protocol.py
carbus_async/tcp_bridge.py
carbus_async/remote/__init__.py
carbus_async/remote/agent.py
carbus_async/remote/client.py
carbus_async/remote/server.py
carbus_lib-0.1.8.dist-info/licenses/LICENSE
isotp_async/__init__.py
isotp_async/api.py
isotp_async/carbus_iface.py
isotp_async/iface.py
isotp_async/transport.py
uds_async/__init__.py
uds_async/client.py
uds_async/exceptions.py
uds_async/server.py
carbus_lib-0.1.8.dist-info/METADATA
carbus_lib-0.1.8.dist-info/WHEEL
carbus_lib-0.1.8.dist-info/entry_points.txt
carbus_lib-0.1.8.dist-info/top_level.txt
carbus_lib-0.1.8.dist-info/RECORD
