Metadata-Version: 2.4
Name: carbus-lib
Version: 0.1.8
Summary: Async CAN / ISO-TP / UDS library for Car Bus Analyzer
Author: Mike
License-Expression: MIT
Project-URL: Homepage, https://github.com/controllerzz/carbus_lib
Requires-Python: >=3.10
License-File: LICENSE
Requires-Dist: pyserial>=3.5
Requires-Dist: pyserial-asyncio>=0.6
Dynamic: license-file
